unusualwhales/__init__.py
unusualwhales/_base_client.py
unusualwhales/_client.py
unusualwhales/_compat.py
unusualwhales/_constants.py
unusualwhales/_exceptions.py
unusualwhales/_files.py
unusualwhales/_models.py
unusualwhales/_qs.py
unusualwhales/_resource.py
unusualwhales/_response.py
unusualwhales/_streaming.py
unusualwhales/_types.py
unusualwhales/_version.py
unusualwhales/py.typed
unusualwhales/_utils/__init__.py
unusualwhales/_utils/_logs.py
unusualwhales/_utils/_proxy.py
unusualwhales/_utils/_reflection.py
unusualwhales/_utils/_streams.py
unusualwhales/_utils/_sync.py
unusualwhales/_utils/_transform.py
unusualwhales/_utils/_typing.py
unusualwhales/_utils/_utils.py
unusualwhales/lib/.keep
unusualwhales/resources/__init__.py
unusualwhales/resources/correlations.py
unusualwhales/resources/insider_trades.py
unusualwhales/resources/analyst/__init__.py
unusualwhales/resources/analyst/analyst.py
unusualwhales/resources/analyst/ratings.py
unusualwhales/resources/analyst/upgrades_downgrades.py
unusualwhales/resources/calendar/__init__.py
unusualwhales/resources/calendar/calendar.py
unusualwhales/resources/calendar/economic.py
unusualwhales/resources/calendar/fda.py
unusualwhales/resources/congress/__init__.py
unusualwhales/resources/congress/congress.py
unusualwhales/resources/congress/members.py
unusualwhales/resources/congress/trades.py
unusualwhales/resources/darkpool/__init__.py
unusualwhales/resources/darkpool/darkpool.py
unusualwhales/resources/darkpool/transactions.py
unusualwhales/resources/etf/__init__.py
unusualwhales/resources/etf/etf.py
unusualwhales/resources/etf/holdings.py
unusualwhales/resources/etf/sectors.py
unusualwhales/resources/etf/tide.py
unusualwhales/resources/institutions/__init__.py
unusualwhales/resources/institutions/activity.py
unusualwhales/resources/institutions/institutions.py
unusualwhales/resources/institutions/trades.py
unusualwhales/resources/market/__init__.py
unusualwhales/resources/market/indices.py
unusualwhales_python-0.1.0a6.dist-info/METADATA
unusualwhales_python-0.1.0a6.dist-info/WHEEL
unusualwhales_python-0.1.0a6.dist-info/licenses/LICENSE
unusualwhales_python-0.1.0a6.dist-info/RECORD
